<?xml version="1.0" encoding="UTF-8"?>
<metadata xml:lang="en"><Esri><CreaDate>20171116</CreaDate><CreaTime>15333900</CreaTime><ArcGISFormat>1.0</ArcGISFormat><SyncOnce>TRUE</SyncOnce><DataProperties><itemProps><itemLocation><linkage Sync="TRUE">file://\\TRIPPSASUS\C$\Student\ArcGISProCookbook\Chapter7\Convert Single Shapefile\Street_Signs_Day1Copy</linkage><protocol Sync="TRUE">Local Area Network</protocol></itemLocation></itemProps><copyHistory><copy source="C:\Student\ArcGISProCookbook\Chapter7\Convert Single Shapefile\Street_Signs_Day1" dest="\\TRIPPSASUS\C$\Student\ArcGISProCookbook\Chapter7\Convert Single Shapefile\Street_Signs_Day1Copy" date="20171116" time="15333900"></copy></copyHistory></DataProperties></Esri></metadata>
